LICENSE
MANIFEST.in
README.md
setup.py
doc/Makefile
doc/build/doctrees/api.doctree
doc/build/doctrees/environment.pickle
doc/build/doctrees/index.doctree
doc/build/doctrees/install.doctree
doc/build/doctrees/what.doctree
doc/build/html/.buildinfo
doc/build/html/api.html
doc/build/html/genindex.html
doc/build/html/index.html
doc/build/html/install.html
doc/build/html/objects.inv
doc/build/html/py-modindex.html
doc/build/html/search.html
doc/build/html/searchindex.js
doc/build/html/what.html
doc/build/html/_modules/database.html
doc/build/html/_modules/detector.html
doc/build/html/_modules/index.html
doc/build/html/_modules/task.html
doc/build/html/_sources/api.txt
doc/build/html/_sources/index.txt
doc/build/html/_sources/install.txt
doc/build/html/_sources/what.txt
doc/build/html/_static/ajax-loader.gif
doc/build/html/_static/basic.css
doc/build/html/_static/classic.css
doc/build/html/_static/comment-bright.png
doc/build/html/_static/comment-close.png
doc/build/html/_static/comment.png
doc/build/html/_static/default.css
doc/build/html/_static/doctools.js
doc/build/html/_static/down-pressed.png
doc/build/html/_static/down.png
doc/build/html/_static/file.png
doc/build/html/_static/jquery-1.11.1.js
doc/build/html/_static/jquery.js
doc/build/html/_static/minus.png
doc/build/html/_static/plus.png
doc/build/html/_static/pygments.css
doc/build/html/_static/searchtools.js
doc/build/html/_static/sidebar.js
doc/build/html/_static/underscore-1.3.1.js
doc/build/html/_static/underscore.js
doc/build/html/_static/up-pressed.png
doc/build/html/_static/up.png
doc/build/html/_static/websupport.js
doc/source/api.rst
doc/source/conf.py
doc/source/index.rst
doc/source/install.rst
doc/source/tools.rst
doc/source/what.rst
doc/source/.backups/index.rst;1
doc/source/.backups/tools.rst.swp
doc/source/.backups/tools.rst;1
doc/source/.backups/tools.rst;10
doc/source/.backups/tools.rst;11
doc/source/.backups/tools.rst;2
doc/source/.backups/tools.rst;3
doc/source/.backups/tools.rst;4
scifig.egg-info/PKG-INFO
scifig.egg-info/SOURCES.txt
scifig.egg-info/dependency_links.txt
scifig.egg-info/top_level.txt
