Metadata-Version: 1.0
Name: scifig
Version: 0.1.3
Summary: A build tool for (non?)-scientific figures
Home-page: https://scifig.readthedocs.org
Author: Francois Boulogne
Author-email: devel@sciunto.org
License: GPLv3
Platform: UNKNOWN
